GAME/__init__.py
GAME/__main__.py
GAME/game.py
GAME/audio/music/Boss_Theme.mp3
GAME/audio/music/Cutman_Stage_Theme.mp3
GAME/audio/music/Ending_theme.mp3
GAME/audio/music/Victory_theme.mp3
GAME/audio/sfx/big_eye_land.wav
GAME/audio/sfx/buster.wav
GAME/audio/sfx/buster_reflect.wav
GAME/audio/sfx/death.wav
GAME/audio/sfx/door.wav
GAME/audio/sfx/enemy_damage.wav
GAME/audio/sfx/enemy_fire.wav
GAME/audio/sfx/megaman_damage.wav
GAME/sprites/Boss_Sprites/Cutman_Idle.png
GAME/sprites/Boss_Sprites/Cutman_Idle_1.png
GAME/sprites/Boss_Sprites/Cutman_Idle_1_us.png
GAME/sprites/Boss_Sprites/Cutman_Idle_us.png
GAME/sprites/Boss_Sprites/Cutman_Jump.png
GAME/sprites/Boss_Sprites/Cutman_Jump_us.png
GAME/sprites/Boss_Sprites/Cutman_Shoot_1.png
GAME/sprites/Boss_Sprites/Cutman_Shoot_2.png
GAME/sprites/Boss_Sprites/Cutman_Walk_1.png
GAME/sprites/Boss_Sprites/Cutman_Walk_1_us.png
GAME/sprites/Boss_Sprites/Cutman_Walk_2.png
GAME/sprites/Boss_Sprites/Cutman_Walk_2_us.png
GAME/sprites/Boss_Sprites/Cutman_Walk_3.png
GAME/sprites/Boss_Sprites/Cutman_Walk_3_us.png
GAME/sprites/Boss_Sprites/Rolling_Cutter.png
GAME/sprites/Ending_Screen/Ending_Screen.png
GAME/sprites/Enemy_Sprites/Big_Eye_Sprites/Grounded.png
GAME/sprites/Enemy_Sprites/Big_Eye_Sprites/Jump.png
GAME/sprites/Enemy_Sprites/Blaster_Sprites/Blaster_0.png
GAME/sprites/Enemy_Sprites/Blaster_Sprites/Blaster_Attack_0.png
GAME/sprites/Enemy_Sprites/Blaster_Sprites/Blaster_Attack_1.png
GAME/sprites/Enemy_Sprites/Blaster_Sprites/Blaster_Attack_2.png
GAME/sprites/Enemy_Sprites/Helicopter_Helicopter_Sprites/Fly_1.png
GAME/sprites/Enemy_Sprites/Helicopter_Helicopter_Sprites/Fly_2.png
GAME/sprites/Enemy_Sprites/Helicopter_Helicopter_Sprites/alueto.kra
GAME/sprites/Enemy_Sprites/Octopus_Sprites/Octopus_Move.png
GAME/sprites/Enemy_Sprites/Octopus_Sprites/Octopus_Sleep.png
GAME/sprites/Enemy_Sprites/Projectiles_Sprites/Blaster_proj.png
GAME/sprites/Megaman_Sprites/Mega_Buster.png
GAME/sprites/Megaman_Sprites/Mega_Jump.png
projeto_mega_homem-1.0.251.dist-info/METADATA
projeto_mega_homem-1.0.251.dist-info/WHEEL
projeto_mega_homem-1.0.251.dist-info/entry_points.txt
projeto_mega_homem-1.0.251.dist-info/RECORD
